repozilla/__init__.py
repozilla/cli.py
repozilla/core.py
repozilla/printer.py
repozilla-0.1.0.dist-info/entry_points.txt
repozilla-0.1.0.dist-info/METADATA
repozilla-0.1.0.dist-info/WHEEL
repozilla-0.1.0.dist-info/RECORD
