Metadata-Version: 2.3
Name: repozilla
Version: 0.1.0
Summary: 🦖 Repozilla – explorador de estruturas de diretórios com estilo
Author: David Closs
Author-email: 100291464+davidcloss@users.noreply.github.com
Requires-Python: >=3.12,<3.13
Classifier: Programming Language :: Python :: 3
Classifier: Programming Language :: Python :: 3.12
Requires-Dist: rich (>=14.0)
